[
   {
      "tag":"热门推荐",
      "tag_en":"Hot"
   },
   {
      "tag":"社区",
      "tag_en":"Community"
   },
   {
      "tag":"钱包",
      "tag_en":"Wallet"
   },
   {
      "tag":"浏览器",
      "tag_en":"Explorer"
   },
   {
      "tag":"资讯",
      "tag_en":"Information"
   },
   {
      "tag":"去中心化交易所",
      "tag_en":"DEX"
   },
   {
      "tag":"借贷",
      "tag_en":"Lending"
   },
   {
      "tag":"衍生品",
      "tag_en":"Derivatives"
   },
   {
      "tag":"稳定币",
      "tag_en":"Stablecoin"
   },
   {
      "tag":"BTC 锚定币",
      "tag_en":"Bitcoin-pegged Token"
   },
   {
      "tag":"资产管理",
      "tag_en":"Asset Management"
   },
   {
      "tag":"其它 DeFi",
      "tag_en":"Other DeFi"
   },
   {
      "tag":"数据分析",
      "tag_en":"Data Analysis"
   },
   {
      "tag":"Rollup",
      "tag_en":"Rollup"
   },
   {
      "tag":"其它 Layer2",
      "tag_en":"Other Layer2"
   },
   {
      "tag":"工具",
      "tag_en":"Tool"
   },
   {
      "tag":"ETH1 客户端",
      "tag_en":"ETH1 Client"
   },
   {
      "tag":"ETH2 客户端",
      "tag_en":"ETH2 Client"
   },
   {
      "tag":"文档",
      "tag_en":"Documentation"
   },
   {
      "tag":"Eth2 资源",
      "tag_en":"Eth2 Resources"
   },
   {
      "tag":"Eth2 质押服务",
      "tag_en":"Eth2 Staking Providers"
   },
   {
      "tag":"开发者",
      "tag_en":"Developer Resources"
   },
   {
      "tag":"安全",
      "tag_en":"Security"
   },
   {
      "tag":"水龙头",
      "tag_en":"Faucets"
   },
   {
      "tag":"基础设施",
      "tag_en":"Infrastructure"
   },
   {
      "tag":"博客",
      "tag_en":"Blog"
   },
   {
      "tag":"播客",
      "tag_en":"Podcast"
   },
   {
      "tag":"会议",
      "tag_en":"Conference"
   },
   {
      "tag":"预言机",
      "tag_en":"Oracle"
   },
   {
      "tag":"隐私",
      "tag_en":"Privacy"
   },
   {
      "tag":"DAO",
      "tag_en":"DAO"
   },
   {
      "tag":"NFT",
      "tag_en":"NFT"
   },
   {
      "tag":"其它应用",
      "tag_en":"Other dApps"
   },
   {
      "tag":"其它",
      "tag_en":"Others"
   }
]
